phanta/__init__.py
phanta/classes.py
phanta/config.json
phanta/decorators.py
phanta/functions.py
phanta/logging.json
phanta/main.py
phanta/pipelines.py
phanta-0.3.dist-info/METADATA
phanta-0.3.dist-info/WHEEL
phanta-0.3.dist-info/top_level.txt
phanta-0.3.dist-info/RECORD
