Metadata-Version: 2.1
Name: phanta
Version: 0.3
Summary: Python package to assemble phage illumina reads
Author: Joshua J Iszatt
Author-email: joshiszatt@gmail.com
Classifier: Development Status :: 4 - Beta
Requires-Python: >=3.10
